README.md
setup.cfg
setup.py
infynipy/__init__.py
infynipy/__version__.py
infynipy/exceptions.py
infynipy/infynity.py
infynipy.egg-info/PKG-INFO
infynipy.egg-info/SOURCES.txt
infynipy.egg-info/dependency_links.txt
infynipy.egg-info/requires.txt
infynipy.egg-info/top_level.txt
infynipy/models/__init__.py
infynipy/models/base.py
infynipy/models/broker.py
infynipy/models/company.py
infynipy/models/group.py
infynipy/models/individual.py
infynipy/models/mixin.py
infynipy/models/referrer.py
infynipy/models/trust.py
infynipy/models/entity/__init__.py
infynipy/models/entity/address.py
infynipy/models/entity/asset.py
infynipy/models/entity/employment.py
infynipy/models/entity/entity.py
infynipy/models/entity/expense.py
infynipy/models/entity/financial.py
infynipy/models/entity/income.py
infynipy/models/entity/liability.py
infynipy/util/__init__.py