Metadata-Version: 2.1
Name: infynipy
Version: 0.1.1
Summary: API Wrapper for the Infynity CRM.
Home-page: https://github.com/beanpuppy/infynipy
Author: Justin Duch
Author-email: justin@justinduch.com
License: MIT
Platform: UNKNOWN
Classifier: License :: OSI Approved :: MIT License
Classifier: Development Status :: 3 - Alpha
Classifier: Intended Audience :: Developers
Classifier: Natural Language :: English
Classifier: Programming Language :: Python :: 3
Classifier: Programming Language :: Python :: 3.5
Classifier: Programming Language :: Python :: 3.6
Classifier: Programming Language :: Python :: 3.7
